langsolution/__init__.py
langsolution-0.0.1.dist-info/METADATA
langsolution-0.0.1.dist-info/WHEEL
langsolution-0.0.1.dist-info/RECORD
