Metadata-Version: 2.4
Name: langsolution
Version: 0.0.1
Summary: Official LangSolution library
Author-email: Darin Tanner <darin.tanner@corp.langsolution.com>
License: Apache License 2.0
Requires-Python: >=3.8
